cause/__init__.py
cause_version/__init__.py
tests/__init__.py
tests/test_dummy.py
cause-0.0.2.dist-info/LICENSE
cause-0.0.2.dist-info/METADATA
cause-0.0.2.dist-info/WHEEL
cause-0.0.2.dist-info/top_level.txt
cause-0.0.2.dist-info/RECORD
